django_redis_views-0.2.2.dist-info/DESCRIPTION.rst
django_redis_views-0.2.2.dist-info/METADATA
django_redis_views-0.2.2.dist-info/metadata.json
django_redis_views-0.2.2.dist-info/pbr.json
django_redis_views-0.2.2.dist-info/RECORD
django_redis_views-0.2.2.dist-info/top_level.txt
django_redis_views-0.2.2.dist-info/WHEEL
redis_views/__init__.py
redis_views/models.py
redis_views/response.py
redis_views/views.py
