Metadata-Version: 2.0
Name: django-redis-views
Version: 0.2.2
Summary: An implementation of the server-side component for Lightning Fast single page app deploys.
Home-page: https://github.com/kevinlondon/django-redis-views
Author: Kevin London
Author-email: kevinlondon@gmail.com
License: BSD
Keywords: django-redis-views
Platform: UNKNOWN
Classifier: Development Status :: 2 - Pre-Alpha
Classifier: Framework :: Django
Classifier: Intended Audience :: Developers
Classifier: License :: OSI Approved :: BSD License
Classifier: Natural Language :: English
Classifier: Programming Language :: Python :: 2
Classifier: Programming Language :: Python :: 2.7
Classifier: Programming Language :: Python :: 3
Classifier: Programming Language :: Python :: 3.3
Classifier: Programming Language :: Python :: 3.4
Requires-Dist: redis (>=2.10.3)
Requires-Dist: django (>=1.5.1)
